examples/__init__.py
examples/custom_default_source/__init__.py
examples/custom_default_source/example_server.py
examples/simple_server/__init__.py
examples/simple_server/example_server.py
examples/structured_response_server/__init__.py
examples/structured_response_server/example_server.py
examples/type_routing/__init__.py
examples/type_routing/example_server.py
fastapi_cloudevents/__init__.py
fastapi_cloudevents/cloudevent.py
fastapi_cloudevents/cloudevent_request.py
fastapi_cloudevents/cloudevent_response.py
fastapi_cloudevents/cloudevent_route.py
fastapi_cloudevents/content_type.py
fastapi_cloudevents/installation.py
fastapi_cloudevents/py.typed
fastapi_cloudevents/settings.py
fastapi_cloudevents-2.0.2.dist-info/LICENSE
fastapi_cloudevents-2.0.2.dist-info/METADATA
fastapi_cloudevents-2.0.2.dist-info/WHEEL
fastapi_cloudevents-2.0.2.dist-info/top_level.txt
fastapi_cloudevents-2.0.2.dist-info/RECORD
