Metadata-Version: 2.1
Name: fastapi-cloudevents
Version: 2.0.2
Summary: FastAPI plugin for CloudEvents Integration
Home-page: https://github.com/sasha-tkachev/fastapi-cloudevents
Author: Alexander Tkachev
Author-email: sasha64sasha@gmail.com
License: UNKNOWN
Keywords: fastapi,cloudevents[pydantic],ce,cloud,events,event,middleware,rest,rest-api,plugin,pydantic,fastapi-extension
Platform: UNKNOWN
Classifier: Intended Audience :: Information Technology
Classifier: Intended Audience :: System Administrators
Classifier: Intended Audience :: Developers
Classifier: License :: OSI Approved :: Apache Software License
Classifier: Development Status :: 5 - Production/Stable
Classifier: Operating System :: OS Independent
Classifier: Programming Language :: Python :: 3
Classifier: Programming Language :: Python :: 3.7
Classifier: Programming Language :: Python :: 3.8
Classifier: Programming Language :: Python :: 3.9
Classifier: Programming Language :: Python :: 3.10
License-File: LICENSE
Requires-Dist: fastapi (>=0.62.0)
Requires-Dist: cloudevents[pydantic]
Requires-Dist: pydantic-settings
